Metadata-Version: 2.1
Name: sphong-colorpalette
Version: 0.0.1
Summary: Python color palettes for scientific publication
Home-page: UNKNOWN
Author: Seungpyo Hong
Author-email: sp1020@gmail.com
License: UNKNOWN
Platform: UNKNOWN
License-File: LICENSE
